hibiapi/__init__.py
hibiapi/__main__.py
hibiapi/api/__init__.py
hibiapi/api/bika/__init__.py
hibiapi/api/bika/api.py
hibiapi/api/bika/constants.py
hibiapi/api/bika/net.py
hibiapi/api/bilibili/__init__.py
hibiapi/api/bilibili/api/__init__.py
hibiapi/api/bilibili/api/base.py
hibiapi/api/bilibili/api/v2.py
hibiapi/api/bilibili/api/v3.py
hibiapi/api/bilibili/constants.py
hibiapi/api/bilibili/net.py
hibiapi/api/netease/__init__.py
hibiapi/api/netease/api.py
hibiapi/api/netease/constants.py
hibiapi/api/netease/net.py
hibiapi/api/pixiv/__init__.py
hibiapi/api/pixiv/api.py
hibiapi/api/pixiv/constants.py
hibiapi/api/pixiv/net.py
hibiapi/api/qrcode.py
hibiapi/api/sauce/__init__.py
hibiapi/api/sauce/api.py
hibiapi/api/sauce/constants.py
hibiapi/api/sauce/net.py
hibiapi/api/tieba/__init__.py
hibiapi/api/tieba/api.py
hibiapi/api/tieba/net.py
hibiapi/api/wallpaper/__init__.py
hibiapi/api/wallpaper/api.py
hibiapi/api/wallpaper/constants.py
hibiapi/api/wallpaper/net.py
hibiapi/app/__init__.py
hibiapi/app/application.py
hibiapi/app/handlers.py
hibiapi/app/middlewares.py
hibiapi/app/routes/__init__.py
hibiapi/app/routes/bika.py
hibiapi/app/routes/bilibili/__init__.py
hibiapi/app/routes/bilibili/v2.py
hibiapi/app/routes/bilibili/v3.py
hibiapi/app/routes/netease.py
hibiapi/app/routes/pixiv.py
hibiapi/app/routes/qrcode.py
hibiapi/app/routes/sauce.py
hibiapi/app/routes/tieba.py
hibiapi/app/routes/wallpaper.py
hibiapi/configs/bika.yml
hibiapi/configs/bilibili.yml
hibiapi/configs/general.yml
hibiapi/configs/netease.yml
hibiapi/configs/pixiv.yml
hibiapi/configs/qrcode.yml
hibiapi/configs/sauce.yml
hibiapi/configs/tieba.yml
hibiapi/configs/wallpaper.yml
hibiapi/utils/__init__.py
hibiapi/utils/cache.py
hibiapi/utils/config.py
hibiapi/utils/decorators/__init__.py
hibiapi/utils/decorators/enum.py
hibiapi/utils/decorators/timer.py
hibiapi/utils/exceptions.py
hibiapi/utils/log.py
hibiapi/utils/net.py
hibiapi/utils/routing.py
hibiapi/utils/temp.py
test/__init__.py
test/test_base.py
HibiAPI-0.8.0.dist-info/entry_points.txt
HibiAPI-0.8.0.dist-info/WHEEL
HibiAPI-0.8.0.dist-info/METADATA
HibiAPI-0.8.0.dist-info/licenses/LICENSE
HibiAPI-0.8.0.dist-info/RECORD
