Metadata-Version: 2.1
Name: HibiAPI
Version: 0.8.0
Summary: A program that implements easy-to-use APIs for a variety of commonly used sites
License: Apache-2.0
Author-email: mixmoe <admin@obfs.dev>
Requires-Python: >=3.8,<4.0
Requires-Dist: cashews[diskcache,redis]<5.0,>=3.3
Requires-Dist: cashews[diskcache,redis]<5.0,>=3.3
Requires-Dist: confuse<2.0.0,>=1.4.0
Requires-Dist: confuse<2.0.0,>=1.4.0
Requires-Dist: fastapi<1.0.0,>=0.85.1
Requires-Dist: fastapi<1.0.0,>=0.85.1
Requires-Dist: httpx[http2]<0.24.0,>=0.21.3
Requires-Dist: httpx[http2]<0.24.0,>=0.21.3
Requires-Dist: loguru<1.0.0,>=0.6.0
Requires-Dist: loguru<1.0.0,>=0.6.0
Requires-Dist: pycryptodomex<4.0.0,>=3.10.1
Requires-Dist: pycryptodomex<4.0.0,>=3.10.1
Requires-Dist: pydantic<2.0.0,>=1.9.0
Requires-Dist: pydantic<2.0.0,>=1.9.0
Requires-Dist: python-dotenv<1.0.0,>=0.21.0
Requires-Dist: python-dotenv<1.0.0,>=0.21.0
Requires-Dist: python-multipart<1.0.0,>=0.0.5
Requires-Dist: python-multipart<1.0.0,>=0.0.5
Requires-Dist: qrcode[pil]<8.0,>=6.1
Requires-Dist: qrcode[pil]<8.0,>=6.1
Requires-Dist: sentry-sdk<2.0.0,>=1.10.1
Requires-Dist: sentry-sdk<2.0.0,>=1.10.1
Requires-Dist: typer[all]<1.0.0,>=0.6.1
Requires-Dist: typer[all]<1.0.0,>=0.6.1
Requires-Dist: typing-extensions>=3.10
Requires-Dist: typing-extensions>=3.10
Requires-Dist: uvicorn[standard]<0.20,>=0.14
Requires-Dist: uvicorn[standard]<0.20,>=0.14
Provides-Extra: scripts
Requires-Dist: pyqt6<7.0.0,>=6.4.0; extra == "scripts"
Requires-Dist: pyqt6-webengine<7.0.0,>=6.4.0; extra == "scripts"
Requires-Dist: requests>=2.28.2; extra == "scripts"
Project-URL: documentation, https://github.com/mixmoe/HibiAPI/wiki
Project-URL: homepage, https://api.obfs.dev
Project-URL: repository, https://github.com/mixmoe/HibiAPI
